moniv/__init__.py
moniv-0.1.0.dist-info/METADATA
moniv-0.1.0.dist-info/WHEEL
moniv-0.1.0.dist-info/top_level.txt
moniv-0.1.0.dist-info/RECORD
