Metadata-Version: 2.4
Name: moniv
Version: 0.1.0
Summary: A lightweight, open-source error tracking and monitoring system.
Home-page: https://github.com/cyberhuginn/moniv
Author: Saleh Azimidokht
Author-email: contact@cyberhuginn.com
Classifier: Programming Language :: Python :: 3
Classifier: License :: OSI Approved :: MIT License
Classifier: Operating System :: OS Independent
Requires-Python: >=3.10
Dynamic: author
Dynamic: author-email
Dynamic: classifier
Dynamic: description
Dynamic: description-content-type
Dynamic: home-page
Dynamic: requires-python
Dynamic: summary
